[{"Name":"Nike React Miler","Price":"$130"},{"Name":"Nike React Infinity Run Flyknit","Price":"$160"},{"Name":"Nike Air Force 1 '07","Price":"$90"},{"Name":"Nike SB Nyjah Free 2","Price":"$95"},{"Name":"Nike Blazer Mid '77 Vintage","Price":"$100"},{"Name":"Air Jordan 1 Low","Price":"$90"},{"Name":"Nike Air Max 2090","Price":"$150"},{"Name":"Nike Air VaporMax Plus","Price":"$200"},{"Name":"Nike Air Vapormax 360","Price":"$225"},{"Name":"LeBron 17 Low","Price":"$160"},{"Name":"Nike Air VaporMax Flyknit 3","Price":"$200"},{"Name":"Nike Air Max 90 N7","Price":"$130"},{"Name":"Kyrie 6 N7","Price":"$130"},{"Name":"Kyrie 6","Price":"$130"},{"Name":"KD13","Price":"$150"},{"Name":"PG 4","Price":"$110"},{"Name":"Nike Air Zoom UNVRS FlyEase","Price":"$160"},{"Name":"Nike Air VaporMax FlyKnit 3 USA","Price":"$200"},{"Name":"Nike Air Max 2090 BETRUE","Price":"$150"},{"Name":"Nike Air Trainer 3","Price":"$130"},{"Name":"Nike Air Zoom Pegasus 37","Price":"$120"},{"Name":"Nike Zoom Fly 3","Price":"$160"},{"Name":"Air Jordan 3 Retro SE","Price":"$250"},{"Name":"Air Jordan 1 Mid","Price":"$115"}]